maxsciencelib/__init__.py
maxsciencelib/_selecao_variavel_impl.py
maxsciencelib/analise_exploratoria.py
maxsciencelib/feature_engineering.py
maxsciencelib/leitura.py
maxsciencelib/machine_learning.py
maxsciencelib/tratamento.py
maxsciencelib/upload.py
maxsciencelib-0.1.15.dist-info/licenses/LICENCE
maxsciencelib-0.1.15.dist-info/METADATA
maxsciencelib-0.1.15.dist-info/WHEEL
maxsciencelib-0.1.15.dist-info/top_level.txt
maxsciencelib-0.1.15.dist-info/RECORD
