Metadata-Version: 2.4
Name: maxsciencelib
Version: 0.1.15
Summary: Biblioteca de funções compartilhadas do time de Data Science da Maxpar
Author-email: Daniel Antunes <daniel.ant.cord@gmail.com>
Requires-Python: >=3.9
License-File: LICENCE
Requires-Dist: pandas>=1.5
Requires-Dist: numpy>=1.23
Requires-Dist: polars>=0.20.0
Requires-Dist: pyarrow>=14.0.0
Requires-Dist: snowflake-connector-python>=3.5.0
Requires-Dist: tableauserverclient>=0.25
Requires-Dist: fastexcel
Provides-Extra: upload
Requires-Dist: selenium>=4.15; extra == "upload"
Provides-Extra: analise-exploratoria
Requires-Dist: matplotlib>=3.7; extra == "analise-exploratoria"
Requires-Dist: seaborn>=0.12; extra == "analise-exploratoria"
Requires-Dist: scipy>=1.10; extra == "analise-exploratoria"
Requires-Dist: scikit-learn>=1.3; extra == "analise-exploratoria"
Requires-Dist: plotly>=5.18; extra == "analise-exploratoria"
Requires-Dist: nbformat>=4.2; extra == "analise-exploratoria"
Requires-Dist: kaleido>=0.2; extra == "analise-exploratoria"
Provides-Extra: tratamento
Requires-Dist: unidecode; extra == "tratamento"
Provides-Extra: estatistica
Requires-Dist: joblib>=1.3; extra == "estatistica"
Provides-Extra: feature-engineering
Requires-Dist: scikit-learn>=1.3; extra == "feature-engineering"
Requires-Dist: lightgbm>=4.0; extra == "feature-engineering"
Requires-Dist: shap>=0.44; extra == "feature-engineering"
Requires-Dist: optuna>=3.4; extra == "feature-engineering"
Requires-Dist: imbalanced-learn>=0.11; extra == "feature-engineering"
Requires-Dist: scipy>=1.10; extra == "feature-engineering"
Requires-Dist: joblib>=1.3; extra == "feature-engineering"
Requires-Dist: matplotlib>=3.7; extra == "feature-engineering"
Requires-Dist: tqdm>=4.65; extra == "feature-engineering"
Requires-Dist: holidays>=0.25; extra == "feature-engineering"
Dynamic: license-file
